{
	"name": "PL123",
	"properties": {
		"activities": [
			{
				"name": "CopyCust_data",
				"type": "Copy",
				"dependsOn": [],
				"policy": {
					"timeout": "0.12:00:00",
					"retry": 0,
					"retryIntervalInSeconds": 30,
					"secureOutput": false,
					"secureInput": false
				},
				"userProperties": [],
				"typeProperties": {
					"source": {
						"type": "DelimitedTextSource",
						"storeSettings": {
							"type": "AzureBlobFSReadSettings",
							"recursive": true,
							"enablePartitionDiscovery": false
						},
						"formatSettings": {
							"type": "DelimitedTextReadSettings"
						}
					},
					"sink": {
						"type": "DelimitedTextSink",
						"storeSettings": {
							"type": "AzureBlobFSWriteSettings"
						},
						"formatSettings": {
							"type": "DelimitedTextWriteSettings",
							"quoteAllText": true,
							"fileExtension": ".csv"
						}
					},
					"enableStaging": false,
					"translator": {
						"type": "TabularTranslator",
						"typeConversion": true,
						"typeConversionSettings": {
							"allowDataTruncation": true,
							"treatBooleanAsNumber": false
						}
					}
				},
				"inputs": [
					{
						"referenceName": "CustCopyINjg186076",
						"type": "DatasetReference"
					}
				],
				"outputs": [
					{
						"referenceName": "copycustOutjg186076",
						"type": "DatasetReference"
					}
				]
			},
			{
				"name": "UC1",
				"type": "DatabricksNotebook",
				"dependsOn": [
					{
						"activity": "LookupCust",
						"dependencyConditions": [
							"Succeeded"
						]
					}
				],
				"policy": {
					"timeout": "0.12:00:00",
					"retry": 0,
					"retryIntervalInSeconds": 30,
					"secureOutput": false,
					"secureInput": false
				},
				"userProperties": [],
				"typeProperties": {
					"notebookPath": "/jg186076/UC1_Jg186076"
				},
				"linkedServiceName": {
					"referenceName": "vf186006_Db_Connection",
					"type": "LinkedServiceReference"
				}
			},
			{
				"name": "LookupCust",
				"type": "Lookup",
				"dependsOn": [
					{
						"activity": "CopyCust_data",
						"dependencyConditions": [
							"Succeeded"
						]
					}
				],
				"policy": {
					"timeout": "0.12:00:00",
					"retry": 0,
					"retryIntervalInSeconds": 30,
					"secureOutput": false,
					"secureInput": false
				},
				"userProperties": [],
				"typeProperties": {
					"source": {
						"type": "DelimitedTextSource",
						"storeSettings": {
							"type": "AzureBlobFSReadSettings",
							"recursive": true,
							"enablePartitionDiscovery": false
						},
						"formatSettings": {
							"type": "DelimitedTextReadSettings"
						}
					},
					"dataset": {
						"referenceName": "copycustOutjg186076_LK",
						"type": "DatasetReference"
					}
				}
			}
		],
		"folder": {
			"name": "jg186076"
		},
		"annotations": []
	}
}